cerealbox/__init__.py
cerealbox/cereal.py
cerealbox/dynamo.py
cerealbox/jsonable.py
cerealbox-0.1.2.dist-info/LICENSE
cerealbox-0.1.2.dist-info/WHEEL
cerealbox-0.1.2.dist-info/METADATA
cerealbox-0.1.2.dist-info/RECORD
