Metadata-Version: 2.1
Name: cerealbox
Version: 0.1.2
Summary: Zero dependency generic serializer and deserializer with DynamoDB JSON support
Home-page: https://github.com/a2d24/cerealbox
License: MIT
Keywords: Serializer,Deserializer,DynamoDB,JSON
Author: Imtiaz Mangerah
Author-email: Imtiaz_Mangerah@a2d24.com
Requires-Python: >=3.8,<4.0
Classifier: License :: OSI Approved :: MIT License
Classifier: Programming Language :: Python :: 3
Classifier: Programming Language :: Python :: 3.8
Classifier: Programming Language :: Python :: 3.9
Project-URL: Documentation, https://github.com/a2d24/cerealbox
